sideload_nu_0_bin_68595bfe8a456b7966b4095e/__init__.py
sideload_nu_0_bin_68595bfe8a456b7966b4095e/nu-0.105.1-x86_64-pc-windows-msvc.zip
sideload_nu_0_bin_68595bfe8a456b7966b4095e-1.0.0.dist-info/METADATA
sideload_nu_0_bin_68595bfe8a456b7966b4095e-1.0.0.dist-info/WHEEL
sideload_nu_0_bin_68595bfe8a456b7966b4095e-1.0.0.dist-info/top_level.txt
sideload_nu_0_bin_68595bfe8a456b7966b4095e-1.0.0.dist-info/RECORD
