Metadata-Version: 2.4
Name: sideload_nu_0_bin_68595bfe8a456b7966b4095e
Version: 1.0.0
Summary: Sideloaded package
Author: Null Void
Requires-Python: >=3.8
